{
  "sector": "Precious Metals",
  "stockCount": 2,
  "lastUpdated": "2025-12-03T22:20:08.366Z",
  "stocks": {
    "NEM": {
      "profile": {
        "symbol": "NEM",
        "price": 89.65,
        "marketCap": 97831726247,
        "beta": 0.441,
        "lastDividend": 1,
        "range": "36.86-98.58",
        "change": -0.83,
        "changePercentage": -0.91733,
        "volume": 5749203,
        "averageVolume": 11438733,
        "companyName": "Newmont Corporation",
        "currency": "USD",
        "cik": "0001164727",
        "isin": "US6516391066",
        "cusip": "651639106",
        "exchangeFullName": "New York Stock Exchange",
        "exchange": "NYSE",
        "industry": "Gold",
        "website": "https://www.newmont.com",
        "description": "Newmont Corporation engages in the production and exploration of gold. It also explores for copper, silver, zinc, and lead. The company has operations and/or assets in the United States, Canada, Mexico, Dominican Republic, Peru, Suriname, Argentina, Chile, Australia, and Ghana. As of December 31, 2021, it had proven and probable gold reserves of 92.8 million ounces and land position of 62,800 square kilometers. The company was founded in 1916 and is headquartered in Denver, Colorado.",
        "ceo": "Thomas Ronald Palmer",
        "sector": "Basic Materials",
        "country": "US",
        "fullTimeEmployees": "22200",
        "phone": "303 863 7414",
        "address": "6900 East Layton Avenue",
        "city": "Denver",
        "state": "CO",
        "zip": "80237",
        "image": "https://images.financialmodelingprep.com/symbol/NEM.png",
        "ipoDate": "1980-03-17",
        "defaultImage": false,
        "isEtf": false,
        "isActivelyTrading": true,
        "isAdr": false,
        "isFund": false
      },
      "ratios": {
        "symbol": "NEM",
        "date": "2024-12-31",
        "fiscalYear": "2024",
        "period": "FY",
        "reportedCurrency": "USD",
        "grossProfitMargin": 0.34617664493183165,
        "ebitMargin": 0.26739235867866573,
        "ebitdaMargin": 0.4238831707711376,
        "operatingProfitMargin": 0.3097483429433637,
        "pretaxProfitMargin": 0.25381257746402974,
        "continuousOperationsProfitMargin": 0.1785310125559088,
        "netProfitMargin": 0.1804170932801638,
        "bottomLineProfitMargin": 0.17675270787303982,
        "receivablesTurnover": 17.572916666666668,
        "payablesTurnover": 14.3926453143535,
        "inventoryTurnover": 5.555402930402931,
        "fixedAssetTurnover": 0.5531642173666795,
        "assetTurnover": 0.32932261442084154,
        "currentRatio": 1.6273366034734191,
        "quickRatio": 1.3377966326395334,
        "solvencyRatio": 0.2382621951219512,
        "cashRatio": 0.47978257987538114,
        "priceToEarningsRatio": 12.740179211469533,
        "priceToEarningsGrowthRatio": -0.06519728421930666,
        "forwardPriceToEarningsGrowthRatio": -0.06519728421930666,
        "priceToBookRatio": 1.425224538893344,
        "priceToSalesRatio": 2.298546101201703,
        "priceToFreeCashFlowRatio": 14.40530901722391,
        "priceToOperatingCashFlowRatio": 6.703460631777463,
        "debtToAssetsRatio": 0.15922199151715202,
        "debtToEquityRatio": 0.29978615343491044,
        "debtToCapitalRatio": 0.2306426735218509,
        "longTermDebtToCapitalRatio": 0.20149413020277482,
        "financialLeverageRatio": 1.8828187650360866,
        "workingCapitalTurnoverRatio": 5.942042907460775,
        "operatingCashFlowRatio": 0.8435635688718016,
        "operatingCashFlowSalesRatio": 0.34288947566955863,
        "freeCashFlowOperatingCashFlowRatio": 0.46534653465346537,
        "debtServiceCoverageRatio": 4.9419404125286475,
        "interestCoverageRatio": 14.92987012987013,
        "shortTermOperatingCashFlowCoverageRatio": 6.886363636363637,
        "operatingCashFlowCoverageRatio": 0.7092064199732501,
        "capitalExpenditureCoverageRatio": 1.8703703703703705,
        "dividendPaidAndCapexCoverageRatio": 1.3993842093688147,
        "dividendPayoutRatio": 0.3419952210274791,
        "dividendYield": 0.026843831264131108,
        "dividendYieldPercentage": 2.6843831264131106,
        "revenuePerShare": 16.19284467713787,
        "netIncomePerShare": 2.9214659685863875,
        "interestDebtPerShare": 8.164921465968586,
        "cashPerShare": 3.176265270506108,
        "bookValuePerShare": 26.273123909249563,
        "tangibleBookValuePerShare": 23.95375218150087,
        "shareholdersEquityPerShare": 26.115183246073297,
        "operatingCashFlowPerShare": 5.552356020942408,
        "capexPerShare": 2.968586387434555,
        "freeCashFlowPerShare": 2.5837696335078535,
        "netIncomePerEBT": 0.710828025477707,
        "ebtPerEbit": 0.8194154488517745,
        "priceToFairValue": 1.425224538893344,
        "debtToMarketCap": 0.19871468453692165,
        "effectiveTaxRate": 0.29660297239915073,
        "enterpriseValueMultiple": 6.103117213323163,
        "dividendPerShare": 0.9991273996509599
      },
      "keyMetrics": {
        "symbol": "NEM",
        "date": "2024-12-31",
        "fiscalYear": "2024",
        "period": "FY",
        "reportedCurrency": "USD",
        "marketCap": 42654120000,
        "enterpriseValue": 48007120000,
        "evToSales": 2.5870086759713318,
        "evToOperatingCashFlow": 7.544730473047305,
        "evToFreeCashFlow": 16.213144208037825,
        "evToEBITDA": 6.103117213323163,
        "netDebtToEBITDA": 0.6805237732011188,
        "currentRatio": 1.6273366034734191,
        "incomeQuality": 1.8819875776397517,
        "grahamNumber": 41.43222091715591,
        "grahamNetNet": -18.076788830715532,
        "taxBurden": 0.710828025477707,
        "interestBurden": 0.9492140266021766,
        "workingCapital": 4732000000,
        "investedCapital": 40937000000,
        "returnOnAssets": 0.05941542884523239,
        "operatingReturnOnAssets": 0.10277591524741854,
        "returnOnTangibleAssets": 0.06235681957870034,
        "returnOnEquity": 0.11186848436246993,
        "returnOnInvestedCapital": 0.08112699630093467,
        "returnOnCapitalEmployed": 0.11777240503216818,
        "earningsYield": 0.0784918315042017,
        "freeCashFlowYield": 0.06941885098086656,
        "capexToOperatingCashFlow": 0.5346534653465347,
        "capexToDepreciation": 1.3206521739130435,
        "capexToRevenue": 0.18332704639758582,
        "salesGeneralAndAdministrativeToRevenue": 0.023818505146305975,
        "researchAndDevelopementToRevenue": 0.01061594007652099,
        "stockBasedCompensationToRevenue": 0.004796033841676995,
        "intangiblesToTotalAssets": 0.047170313581430014,
        "averageReceivables": 1141500000,
        "averagePayables": 901500000,
        "averageInventory": 2413000000,
        "daysOfSalesOutstanding": 20.7705986959099,
        "daysOfPayablesOutstanding": 25.360174730075002,
        "daysOfInventoryOutstanding": 65.70180499464271,
        "operatingCycle": 86.47240369055261,
        "cashConversionCycle": 61.11222896047761,
        "freeCashFlowToEquity": -2392000000,
        "freeCashFlowToFirm": -225743949.04458618,
        "tangibleAssetValue": 27451000000,
        "netCurrentAssetValue": -13965000000
      },
      "incomeStatement": {
        "date": "2024-12-31",
        "symbol": "NEM",
        "reportedCurrency": "USD",
        "cik": "0001164727",
        "filingDate": "2025-02-21",
        "acceptedDate": "2025-02-20 20:20:57",
        "fiscalYear": "2024",
        "period": "FY",
        "revenue": 18557000000,
        "costOfRevenue": 12133000000,
        "grossProfit": 6424000000,
        "researchAndDevelopmentExpenses": 197000000,
        "generalAndAdministrativeExpenses": 442000000,
        "sellingAndMarketingExpenses": 0,
        "sellingGeneralAndAdministrativeExpenses": 442000000,
        "otherExpenses": 37000000,
        "operatingExpenses": 676000000,
        "costAndExpenses": 12809000000,
        "netInterestIncome": -233000000,
        "interestIncome": 152000000,
        "interestExpense": 385000000,
        "depreciationAndAmortization": 2904000000,
        "ebitda": 7866000000,
        "ebit": 4962000000,
        "nonOperatingIncomeExcludingInterest": 786000000,
        "operatingIncome": 5748000000,
        "totalOtherIncomeExpensesNet": -1038000000,
        "incomeBeforeTax": 4710000000,
        "incomeTaxExpense": 1397000000,
        "netIncomeFromContinuingOperations": 3313000000,
        "netIncomeFromDiscontinuedOperations": 68000000,
        "otherAdjustmentsToNetIncome": 0,
        "netIncome": 3348000000,
        "netIncomeDeductions": 0,
        "bottomLineNetIncome": 3280000000,
        "eps": 2.86,
        "epsDiluted": 2.86,
        "weightedAverageShsOut": 1146000000,
        "weightedAverageShsOutDil": 1148000000
      },
      "incomeStatementHistory": [
        {
          "date": "2024-12-31",
          "symbol": "NEM",
          "reportedCurrency": "USD",
          "cik": "0001164727",
          "filingDate": "2025-02-21",
          "acceptedDate": "2025-02-20 20:20:57",
          "fiscalYear": "2024",
          "period": "FY",
          "revenue": 18557000000,
          "costOfRevenue": 12133000000,
          "grossProfit": 6424000000,
          "researchAndDevelopmentExpenses": 197000000,
          "generalAndAdministrativeExpenses": 442000000,
          "sellingAndMarketingExpenses": 0,
          "sellingGeneralAndAdministrativeExpenses": 442000000,
          "otherExpenses": 37000000,
          "operatingExpenses": 676000000,
          "costAndExpenses": 12809000000,
          "netInterestIncome": -233000000,
          "interestIncome": 152000000,
          "interestExpense": 385000000,
          "depreciationAndAmortization": 2904000000,
          "ebitda": 7866000000,
          "ebit": 4962000000,
          "nonOperatingIncomeExcludingInterest": 786000000,
          "operatingIncome": 5748000000,
          "totalOtherIncomeExpensesNet": -1038000000,
          "incomeBeforeTax": 4710000000,
          "incomeTaxExpense": 1397000000,
          "netIncomeFromContinuingOperations": 3313000000,
          "netIncomeFromDiscontinuedOperations": 68000000,
          "otherAdjustmentsToNetIncome": 0,
          "netIncome": 3348000000,
          "netIncomeDeductions": 0,
          "bottomLineNetIncome": 3280000000,
          "eps": 2.86,
          "epsDiluted": 2.86,
          "weightedAverageShsOut": 1146000000,
          "weightedAverageShsOutDil": 1148000000
        },
        {
          "date": "2023-12-31",
          "symbol": "NEM",
          "reportedCurrency": "USD",
          "cik": "0001164727",
          "filingDate": "2024-02-29",
          "acceptedDate": "2024-02-29 07:51:31",
          "fiscalYear": "2023",
          "period": "FY",
          "revenue": 11775000000,
          "costOfRevenue": 10605000000,
          "grossProfit": 1170000000,
          "researchAndDevelopmentExpenses": 200000000,
          "generalAndAdministrativeExpenses": 0,
          "sellingAndMarketingExpenses": 0,
          "sellingGeneralAndAdministrativeExpenses": 299000000,
          "otherExpenses": 21000000,
          "operatingExpenses": 520000000,
          "costAndExpenses": 11125000000,
          "netInterestIncome": -100000000,
          "interestIncome": 148000000,
          "interestExpense": 248000000,
          "depreciationAndAmortization": 3641000000,
          "ebitda": 1858000000,
          "ebit": -1783000000,
          "nonOperatingIncomeExcludingInterest": 2433000000,
          "operatingIncome": 650000000,
          "totalOtherIncomeExpensesNet": -2618000000,
          "incomeBeforeTax": -1968000000,
          "incomeTaxExpense": 526000000,
          "netIncomeFromContinuingOperations": -2494000000,
          "netIncomeFromDiscontinuedOperations": 0,
          "otherAdjustmentsToNetIncome": 0,
          "netIncome": -2521000000,
          "netIncomeDeductions": 0,
          "bottomLineNetIncome": -2521000000,
          "eps": -2.9976,
          "epsDiluted": -2.9976,
          "weightedAverageShsOut": 841000000,
          "weightedAverageShsOutDil": 841000000
        }
      ],
      "analystEstimates": {
        "symbol": "NEM",
        "date": "2029-12-31",
        "revenueLow": 20068903582,
        "revenueHigh": 24363027249,
        "revenueAvg": 22457511450,
        "ebitdaLow": 7406831809,
        "ebitdaHigh": 8991664365,
        "ebitdaAvg": 8288395501,
        "ebitLow": 2184275379,
        "ebitHigh": 2651642645,
        "ebitAvg": 2444248593,
        "netIncomeLow": 6934758046,
        "netIncomeHigh": 8935159527,
        "netIncomeAvg": 8047480007,
        "sgaExpenseLow": 470084899,
        "sgaExpenseHigh": 570668505,
        "sgaExpenseAvg": 526034567,
        "epsAvg": 7.01,
        "epsHigh": 7.78324,
        "epsLow": 6.04073,
        "numAnalystsRevenue": 10,
        "numAnalystsEps": 4
      },
      "lastUpdated": "2025-12-03T22:19:31.500Z"
    },
    "GOLD": {
      "profile": {
        "symbol": "GOLD",
        "price": 21.155,
        "marketCap": 36375176300,
        "beta": 0.32,
        "lastDividend": 0.4,
        "range": "15.11-21.56",
        "change": 0.285,
        "changePercentage": 1.3656,
        "volume": 4525764,
        "averageVolume": 24581381,
        "companyName": "Barrick Gold Corporation",
        "currency": "USD",
        "cik": "0000756894",
        "isin": "CA06849F1080",
        "cusip": "06849F108",
        "exchangeFullName": "New York Stock Exchange",
        "exchange": "NYSE",
        "industry": "Gold",
        "website": "https://www.barrick.com",
        "description": "Barrick Gold Corporation engages in the exploration, mine development, production, and sale of gold and copper properties. It has ownership interests in producing gold mines that are located in Argentina, Canada, Côte d'Ivoire, the Democratic Republic of Congo, Dominican Republic, Mali, Tanzania, and the United States. The company also has ownership interests in producing copper mines located in Chile, Saudi Arabia, and Zambia; and various other projects located throughout the Americas and Africa. Barrick Gold Corporation was founded in 1983 and is headquartered in Toronto, Canada.",
        "ceo": "Dennis Mark Bristow",
        "sector": "Basic Materials",
        "country": "CA",
        "fullTimeEmployees": "22100",
        "phone": "14163077470",
        "address": "TD Canada Trust Tower",
        "city": "Toronto",
        "state": "ON",
        "zip": "M5J 2S1",
        "image": "https://images.financialmodelingprep.com/symbol/GOLD.png",
        "ipoDate": "1985-02-13",
        "defaultImage": false,
        "isEtf": false,
        "isActivelyTrading": false,
        "isAdr": false,
        "isFund": false
      },
      "ratios": {
        "symbol": "GOLD",
        "date": "2024-12-31",
        "fiscalYear": "2024",
        "period": "FY",
        "reportedCurrency": "USD",
        "grossProfitMargin": 0.38391889800340506,
        "ebitMargin": 0.3893360160965795,
        "ebitdaMargin": 0.5052408352422225,
        "operatingProfitMargin": 0.3332301501315586,
        "pretaxProfitMargin": 0.3566011453335397,
        "continuousOperationsProfitMargin": 0.2389722953103235,
        "netProfitMargin": 0.16591858845379973,
        "bottomLineProfitMargin": 0.16591858845379973,
        "receivablesTurnover": 9.480557593543654,
        "payablesTurnover": 12.154198473282444,
        "inventoryTurnover": 4.0993820803295575,
        "fixedAssetTurnover": 0.4511713976467302,
        "assetTurnover": 0.271322386931508,
        "currentRatio": 2.8887206661619986,
        "quickRatio": 2.1536714610143832,
        "solvencyRatio": 0.2824634655532359,
        "cashRatio": 1.542013626040878,
        "priceToEarningsRatio": 12.658815298507463,
        "priceToEarningsGrowthRatio": 0.18228694029850748,
        "forwardPriceToEarningsGrowthRatio": 0.18228694029850748,
        "priceToBookRatio": 1.1173528200905722,
        "priceToSalesRatio": 2.1003327658257236,
        "priceToFreeCashFlowRatio": 20.60782080485953,
        "priceToOperatingCashFlowRatio": 6.043308839902026,
        "debtToAssetsRatio": 0.11035988745643135,
        "debtToEquityRatio": 0.2163853437628654,
        "debtToCapitalRatio": 0.1778921004535301,
        "longTermDebtToCapitalRatio": 0.1742589067174327,
        "financialLeverageRatio": 1.9607245780156444,
        "workingCapitalTurnoverRatio": 2.5659253375694995,
        "operatingCashFlowRatio": 1.6998485995457986,
        "operatingCashFlowSalesRatio": 0.3475468193778053,
        "freeCashFlowOperatingCashFlowRatio": 0.29325317301269205,
        "debtServiceCoverageRatio": 10.468639624470127,
        "interestCoverageRatio": 10.56816429400743,
        "shortTermOperatingCashFlowCoverageRatio": 63.25352112676056,
        "operatingCashFlowCoverageRatio": 0.8544520547945206,
        "capitalExpenditureCoverageRatio": 1.4149338374291116,
        "dividendPaidAndCapexCoverageRatio": 1.1604651162790698,
        "dividendPayoutRatio": 0.3246268656716418,
        "dividendYield": 0.025644332270960375,
        "dividendYieldPercentage": 2.5644332270960373,
        "revenuePerShare": 7.379782981153626,
        "netIncomePerShare": 1.2244431753283838,
        "interestDebtPerShare": 3.2344089880068534,
        "cashPerShare": 2.3266704740148487,
        "bookValuePerShare": 18.992575671045117,
        "tangibleBookValuePerShare": 17.18617932609937,
        "shareholdersEquityPerShare": 13.872073101085094,
        "operatingCashFlowPerShare": 2.564820102798401,
        "capexPerShare": 1.812678469446031,
        "freeCashFlowPerShare": 0.75214163335237,
        "netIncomePerEBT": 0.4652777777777778,
        "ebtPerEbit": 1.0701346957733395,
        "priceToFairValue": 1.1173528200905722,
        "debtToMarketCap": 0.19148505001750152,
        "effectiveTaxRate": 0.3298611111111111,
        "enterpriseValueMultiple": 4.338138411057462,
        "dividendPerShare": 0.3974871501998858
      },
      "keyMetrics": {
        "symbol": "GOLD",
        "date": "2024-12-31",
        "fiscalYear": "2024",
        "period": "FY",
        "reportedCurrency": "USD",
        "marketCap": 27140500000,
        "enterpriseValue": 28322500000,
        "evToSales": 2.1918046741990405,
        "evToOperatingCashFlow": 6.3065018926742376,
        "evToFreeCashFlow": 21.50531511009871,
        "evToEBITDA": 4.338138411057462,
        "netDebtToEBITDA": 0.18104615065301158,
        "currentRatio": 2.8887206661619986,
        "incomeQuality": 1.454339378238342,
        "grahamNumber": 19.549302233489104,
        "grahamNetNet": -4.7417190177041695,
        "taxBurden": 0.4652777777777778,
        "interestBurden": 0.9159212880143113,
        "workingCapital": 4990000000,
        "investedCapital": 36794000000,
        "returnOnAssets": 0.04501742745559149,
        "operatingReturnOnAssets": 0.0921690550852446,
        "returnOnTangibleAssets": 0.0482198682050244,
        "returnOnEquity": 0.08826677645121449,
        "returnOnInvestedCapital": 0.06402809211759021,
        "returnOnCapitalEmployed": 0.09572292370620665,
        "earningsYield": 0.0789963338921538,
        "freeCashFlowYield": 0.04852526666789484,
        "capexToOperatingCashFlow": 0.706746826987308,
        "capexToDepreciation": 1.6574412532637075,
        "capexToRevenue": 0.24562761182479492,
        "salesGeneralAndAdministrativeToRevenue": 0.00889955115307228,
        "researchAndDevelopementToRevenue": 0,
        "stockBasedCompensationToRevenue": 0.005030181086519115,
        "intangiblesToTotalAssets": 0.06641330365766598,
        "averageReceivables": 1267486499,
        "averagePayables": 666500000,
        "averageInventory": 1862000000,
        "daysOfSalesOutstanding": 38.49984522519733,
        "daysOfPayablesOutstanding": 30.03077502826278,
        "daysOfInventoryOutstanding": 89.03780932043713,
        "operatingCycle": 127.53765454563447,
        "cashConversionCycle": 97.50687951737169,
        "freeCashFlowToEquity": 135000000,
        "freeCashFlowToFirm": 2204468750,
        "tangibleAssetValue": 30093000000,
        "netCurrentAssetValue": -6738000000
      },
      "incomeStatement": {
        "date": "2024-12-31",
        "symbol": "GOLD",
        "reportedCurrency": "USD",
        "cik": "0000756894",
        "filingDate": "2025-03-14",
        "acceptedDate": "2025-03-14 09:12:48",
        "fiscalYear": "2024",
        "period": "FY",
        "revenue": 12922000000,
        "costOfRevenue": 7961000000,
        "grossProfit": 4961000000,
        "researchAndDevelopmentExpenses": 0,
        "generalAndAdministrativeExpenses": 115000000,
        "sellingAndMarketingExpenses": 0,
        "sellingGeneralAndAdministrativeExpenses": 115000000,
        "otherExpenses": 540000000,
        "operatingExpenses": 655000000,
        "costAndExpenses": 8616000000,
        "netInterestIncome": -123758219,
        "interestIncome": 283691918,
        "interestExpense": 407450138,
        "depreciationAndAmortization": 1915000000,
        "ebitda": 6528722073,
        "ebit": 5031000000,
        "nonOperatingIncomeExcludingInterest": -787000000,
        "operatingIncome": 4306000000,
        "totalOtherIncomeExpensesNet": 424000000,
        "incomeBeforeTax": 4608000000,
        "incomeTaxExpense": 1520000000,
        "netIncomeFromContinuingOperations": 3088000000,
        "netIncomeFromDiscontinuedOperations": 0,
        "otherAdjustmentsToNetIncome": 0,
        "netIncome": 2144000000,
        "netIncomeDeductions": 0,
        "bottomLineNetIncome": 2144000000,
        "eps": 1.22,
        "epsDiluted": 1.22,
        "weightedAverageShsOut": 1751000000,
        "weightedAverageShsOutDil": 1751000000
      },
      "incomeStatementHistory": [
        {
          "date": "2024-12-31",
          "symbol": "GOLD",
          "reportedCurrency": "USD",
          "cik": "0000756894",
          "filingDate": "2025-03-14",
          "acceptedDate": "2025-03-14 09:12:48",
          "fiscalYear": "2024",
          "period": "FY",
          "revenue": 12922000000,
          "costOfRevenue": 7961000000,
          "grossProfit": 4961000000,
          "researchAndDevelopmentExpenses": 0,
          "generalAndAdministrativeExpenses": 115000000,
          "sellingAndMarketingExpenses": 0,
          "sellingGeneralAndAdministrativeExpenses": 115000000,
          "otherExpenses": 540000000,
          "operatingExpenses": 655000000,
          "costAndExpenses": 8616000000,
          "netInterestIncome": -123758219,
          "interestIncome": 283691918,
          "interestExpense": 407450138,
          "depreciationAndAmortization": 1915000000,
          "ebitda": 6528722073,
          "ebit": 5031000000,
          "nonOperatingIncomeExcludingInterest": -787000000,
          "operatingIncome": 4306000000,
          "totalOtherIncomeExpensesNet": 424000000,
          "incomeBeforeTax": 4608000000,
          "incomeTaxExpense": 1520000000,
          "netIncomeFromContinuingOperations": 3088000000,
          "netIncomeFromDiscontinuedOperations": 0,
          "otherAdjustmentsToNetIncome": 0,
          "netIncome": 2144000000,
          "netIncomeDeductions": 0,
          "bottomLineNetIncome": 2144000000,
          "eps": 1.22,
          "epsDiluted": 1.22,
          "weightedAverageShsOut": 1751000000,
          "weightedAverageShsOutDil": 1751000000
        },
        {
          "date": "2023-12-31",
          "symbol": "GOLD",
          "reportedCurrency": "USD",
          "cik": "0000756894",
          "filingDate": "2024-03-15",
          "acceptedDate": "2024-03-15 07:31:51",
          "fiscalYear": "2023",
          "period": "FY",
          "revenue": 11397000000,
          "costOfRevenue": 7932000000,
          "grossProfit": 3465000000,
          "researchAndDevelopmentExpenses": 0,
          "generalAndAdministrativeExpenses": 126000000,
          "sellingAndMarketingExpenses": 0,
          "sellingGeneralAndAdministrativeExpenses": 126000000,
          "otherExpenses": 3329000000,
          "operatingExpenses": 3465000000,
          "costAndExpenses": 8744475405,
          "netInterestIncome": -65173684,
          "interestIncome": 295318256,
          "interestExpense": 360491940,
          "depreciationAndAmortization": 2169061676,
          "ebitda": 5158904438,
          "ebit": 2989842762,
          "nonOperatingIncomeExcludingInterest": -520842762,
          "operatingIncome": 2469000000,
          "totalOtherIncomeExpensesNet": 345000000,
          "incomeBeforeTax": 2814000000,
          "incomeTaxExpense": 861000000,
          "netIncomeFromContinuingOperations": 1953000000,
          "netIncomeFromDiscontinuedOperations": 0,
          "otherAdjustmentsToNetIncome": 12488733,
          "netIncome": 1272000000,
          "netIncomeDeductions": 0,
          "bottomLineNetIncome": 1272000000,
          "eps": 0.72,
          "epsDiluted": 0.72,
          "weightedAverageShsOut": 1755000000,
          "weightedAverageShsOutDil": 1755000000
        }
      ],
      "analystEstimates": {
        "symbol": "GOLD",
        "date": "2029-12-31",
        "revenueLow": 15609273844,
        "revenueHigh": 20077342612,
        "revenueAvg": 17354730784,
        "ebitdaLow": 7685911400,
        "ebitdaHigh": 9885961257,
        "ebitdaAvg": 8545363770,
        "ebitLow": 4891909189,
        "ebitHigh": 6292191283,
        "ebitAvg": 5438931230,
        "netIncomeLow": 2466651211,
        "netIncomeHigh": 3416393611,
        "netIncomeAvg": 2837670601,
        "sgaExpenseLow": 192556082,
        "sgaExpenseHigh": 247674201,
        "sgaExpenseAvg": 214088047,
        "epsAvg": 1.6206,
        "epsHigh": 1.95111,
        "epsLow": 1.40871,
        "numAnalystsRevenue": 12,
        "numAnalystsEps": 9
      },
      "lastUpdated": "2025-12-03T22:19:33.455Z"
    }
  }
}